{
  "AAVEUSDT": {
    "createdAt": 1667194068698,
    "lastPrice": 83.77
  },
  "ATOMUSDT": {
    "createdAt": 1667194141999,
    "lastPrice": 14.258
  },
  "ETHUSDT": {
    "createdAt": 1667193951443,
    "lastPrice": 1591.98
  },
  "DEFIUSDT": {
    "createdAt": 1667194325540,
    "lastPrice": 703.2
  },
  "1000SHIBUSDT": {
    "createdAt": 1667194036711,
    "lastPrice": 0.012198
  },
  "UNIUSDT": {
    "createdAt": 1667193866511,
    "lastPrice": 6.888
  },
  "LINKUSDT": {
    "createdAt": 1667194090660,
    "lastPrice": 7.944
  },
  "ARUSDT": {
    "createdAt": 1667193989522,
    "lastPrice": 10.265
  },
  "ALGOUSDT": {
    "createdAt": 1667194423710,
    "lastPrice": 0.362
  },
  "LRCUSDT": {
    "createdAt": 1667193900652,
    "lastPrice": 0.2797
  },
  "CRVUSDT": {
    "createdAt": 1667194028903,
    "lastPrice": 0.901
  },
  "MATICUSDT": {
    "createdAt": 1667194095559,
    "lastPrice": 0.9111
  },
  "XLMUSDT": {
    "createdAt": 1667194086975,
    "lastPrice": 0.1111
  },
  "SRMUSDT": {
    "createdAt": 1667193964455,
    "lastPrice": 0.7822
  },
  "BNBUSDT": {
    "createdAt": 1667194068696,
    "lastPrice": 311.24
  },
  "XTZUSDT": {
    "createdAt": 1667193982569,
    "lastPrice": 1.436
  },
  "IOTAUSDT": {
    "createdAt": 1667194384074,
    "lastPrice": 0.2611
  },
  "EGLDUSDT": {
    "createdAt": 1667194001776,
    "lastPrice": 59.51
  },
  "ETHUSDT_220930": {
    "createdAt": 1661355032968,
    "lastPrice": 1654.4
  },
  "BATUSDT": {
    "createdAt": 1667193919570,
    "lastPrice": 0.2963
  },
  "TRXUSDT": {
    "createdAt": 1667194361644,
    "lastPrice": 0.06289
  },
  "BTCDOMUSDT": {
    "createdAt": 1667194433901,
    "lastPrice": 1205.9
  },
  "XEMUSDT": {
    "createdAt": 1667194295597,
    "lastPrice": 0.0393
  },
  "BTSUSDT": {
    "createdAt": 1661224802015,
    "lastPrice": 0.01251
  },
  "ICPUSDT": {
    "createdAt": 1661224802016,
    "lastPrice": 6.44
  },
  "SCUSDT": {
    "createdAt": 1661393402419,
    "lastPrice": 0.003653
  },
  "TLMUSDT": {
    "createdAt": 1661396102127,
    "lastPrice": 0.0347
  },
  "BTCSTUSDT": {
    "createdAt": 1661224802013,
    "lastPrice": 319.408
  },
  "CTSIUSDT": {
    "createdAt": 1667193902074,
    "lastPrice": 0.1425
  },
  "DENTUSDT": {
    "createdAt": 1667193915442,
    "lastPrice": 0.000885
  },
  "MKRUSDT": {
    "createdAt": 1667194197305,
    "lastPrice": 909.8
  },
  "ONTUSDT": {
    "createdAt": 1667193930750,
    "lastPrice": 0.2256
  },
  "THETAUSDT": {
    "createdAt": 1667194121609,
    "lastPrice": 1.175
  },
  "CELOUSDT": {
    "createdAt": 1667194008728,
    "lastPrice": 0.716
  },
  "RENUSDT": {
    "createdAt": 1667194050267,
    "lastPrice": 0.1273
  },
  "ENJUSDT": {
    "createdAt": 1667194214310,
    "lastPrice": 0.4602
  },
  "HBARUSDT": {
    "createdAt": 1667194214315,
    "lastPrice": 0.06064
  },
  "ZILUSDT": {
    "createdAt": 1667194091315,
    "lastPrice": 0.03098
  },
  "NEOUSDT": {
    "createdAt": 1667194140185,
    "lastPrice": 8.498
  },
  "BALUSDT": {
    "createdAt": 1667194154723,
    "lastPrice": 6.74
  },
  "ZRXUSDT": {
    "createdAt": 1667194236990,
    "lastPrice": 0.2517
  },
  "ICXUSDT": {
    "createdAt": 1667194202064,
    "lastPrice": 0.2332
  },
  "SOLUSDT": {
    "createdAt": 1667194153295,
    "lastPrice": 33.19
  },
  "APEUSDT": {
    "createdAt": 1667194360653,
    "lastPrice": 4.812
  },
  "XRPUSDT": {
    "createdAt": 1667194068693,
    "lastPrice": 0.4594
  },
  "JASMYUSDT": {
    "createdAt": 1667194001138,
    "lastPrice": 0.005231
  },
  "AVAXUSDT": {
    "createdAt": 1667194255062,
    "lastPrice": 18.731
  },
  "BTCUSDT": {
    "createdAt": 1667193952528,
    "lastPrice": 20562
  },
  "GALUSDT": {
    "createdAt": 1667193984075,
    "lastPrice": 2.1767
  },
  "DOGEUSDT": {
    "createdAt": 1667194383476,
    "lastPrice": 0.1225
  },
  "BTCUSDT_220930": {
    "createdAt": 1661355030746,
    "lastPrice": 21591.3
  },
  "KNCUSDT": {
    "createdAt": 1667194240660,
    "lastPrice": 0.911
  },
  "CVCUSDT": {
    "createdAt": 1667194021858,
    "lastPrice": 0.12297
  },
  "MASKUSDT": {
    "createdAt": 1667194373350,
    "lastPrice": 2.197
  },
  "ENSUSDT": {
    "createdAt": 1667194360659,
    "lastPrice": 17.171
  },
  "LTCUSDT": {
    "createdAt": 1667194308650,
    "lastPrice": 55.25
  },
  "YFIUSDT": {
    "createdAt": 1667194139952,
    "lastPrice": 8216
  },
  "GTCUSDT": {
    "createdAt": 1667194449646,
    "lastPrice": 1.917
  },
  "STORJUSDT": {
    "createdAt": 1667194433554,
    "lastPrice": 0.432
  },
  "GRTUSDT": {
    "createdAt": 1667194171901,
    "lastPrice": 0.08335
  },
  "BCHUSDT": {
    "createdAt": 1667194325630,
    "lastPrice": 116.5
  },
  "FILUSDT": {
    "createdAt": 1667194316900,
    "lastPrice": 5.406
  },
  "MANAUSDT": {
    "createdAt": 1667194391007,
    "lastPrice": 0.6776
  },
  "QTUMUSDT": {
    "createdAt": 1667194202068,
    "lastPrice": 2.869
  },
  "SUSHIUSDT": {
    "createdAt": 1667194050272,
    "lastPrice": 1.661
  },
  "ZENUSDT": {
    "createdAt": 1667194360832,
    "lastPrice": 13.623
  },
  "IMXUSDT": {
    "createdAt": 1667194196085,
    "lastPrice": 0.6006
  },
  "KSMUSDT": {
    "createdAt": 1667194154756,
    "lastPrice": 36.05
  },
  "RSRUSDT": {
    "createdAt": 1667194088858,
    "lastPrice": 0.006262
  },
  "FTMUSDT": {
    "createdAt": 1667194370736,
    "lastPrice": 0.2377
  },
  "ZECUSDT": {
    "createdAt": 1667194225912,
    "lastPrice": 53.6
  },
  "COTIUSDT": {
    "createdAt": 1667194397147,
    "lastPrice": 0.10439
  },
  "KAVAUSDT": {
    "createdAt": 1667194218910,
    "lastPrice": 1.4785
  },
  "SXPUSDT": {
    "createdAt": 1667194344949,
    "lastPrice": 0.3277
  },
  "KLAYUSDT": {
    "createdAt": 1667193956907,
    "lastPrice": 0.2823
  },
  "ADAUSDT": {
    "createdAt": 1667194104140,
    "lastPrice": 0.4031
  },
  "FTTUSDT": {
    "createdAt": 1667194128742,
    "lastPrice": 25.645
  },
  "ONEUSDT": {
    "createdAt": 1667194236567,
    "lastPrice": 0.01911
  },
  "MTLUSDT": {
    "createdAt": 1667194233552,
    "lastPrice": 0.9951
  },
  "DASHUSDT": {
    "createdAt": 1667194090668,
    "lastPrice": 41.97
  },
  "XMRUSDT": {
    "createdAt": 1667193960219,
    "lastPrice": 148.5
  },
  "STMXUSDT": {
    "createdAt": 1667194255832,
    "lastPrice": 0.00687
  },
  "CHRUSDT": {
    "createdAt": 1667194154730,
    "lastPrice": 0.1519
  },
  "DOTUSDT": {
    "createdAt": 1667194269274,
    "lastPrice": 6.702
  },
  "AXSUSDT": {
    "createdAt": 1667194383475,
    "lastPrice": 9.2
  },
  "RUNEUSDT": {
    "createdAt": 1667194258696,
    "lastPrice": 1.567
  },
  "LINAUSDT": {
    "createdAt": 1667193970326,
    "lastPrice": 0.00807
  },
  "VETUSDT": {
    "createdAt": 1667194373354,
    "lastPrice": 0.0237
  },
  "OGNUSDT": {
    "createdAt": 1667193929571,
    "lastPrice": 0.1488
  },
  "C98USDT": {
    "createdAt": 1667194002605,
    "lastPrice": 0.33
  },
  "ARPAUSDT": {
    "createdAt": 1667194225230,
    "lastPrice": 0.03467
  },
  "INJUSDT": {
    "createdAt": 1667194437607,
    "lastPrice": 2.245
  },
  "REEFUSDT": {
    "createdAt": 1667194148842,
    "lastPrice": 0.005226
  },
  "DARUSDT": {
    "createdAt": 1667193981325,
    "lastPrice": 0.2112
  },
  "DGBUSDT": {
    "createdAt": 1667193961361,
    "lastPrice": 0.00915
  },
  "EOSUSDT": {
    "createdAt": 1667194319177,
    "lastPrice": 1.121
  },
  "ANTUSDT": {
    "createdAt": 1667194259950,
    "lastPrice": 1.81
  },
  "1000XECUSDT": {
    "createdAt": 1667193960363,
    "lastPrice": 0.03804
  },
  "IOSTUSDT": {
    "createdAt": 1667194384080,
    "lastPrice": 0.011418
  },
  "SNXUSDT": {
    "createdAt": 1667194414242,
    "lastPrice": 2.444
  },
  "FLOWUSDT": {
    "createdAt": 1667193858802,
    "lastPrice": 1.687
  },
  "NEARUSDT": {
    "createdAt": 1667194303090,
    "lastPrice": 3.091
  },
  "STGUSDT": {
    "createdAt": 1667193961900,
    "lastPrice": 0.4998
  },
  "ANKRUSDT": {
    "createdAt": 1667194273267,
    "lastPrice": 0.02902
  },
  "ETCUSDT": {
    "createdAt": 1667194145899,
    "lastPrice": 24.322
  },
  "RVNUSDT": {
    "createdAt": 1667194078485,
    "lastPrice": 0.03212
  },
  "TRBUSDT": {
    "createdAt": 1667194296494,
    "lastPrice": 15.98
  },
  "BNXUSDT": {
    "createdAt": 1667194088857,
    "lastPrice": 144.56
  },
  "SPELLUSDT": {
    "createdAt": 1667193973521,
    "lastPrice": 0.000873
  },
  "BELUSDT": {
    "createdAt": 1667194212221,
    "lastPrice": 0.5706
  },
  "DUSKUSDT": {
    "createdAt": 1667194126116,
    "lastPrice": 0.13083
  },
  "BANDUSDT": {
    "createdAt": 1667194235901,
    "lastPrice": 1.1789
  },
  "CTKUSDT": {
    "createdAt": 1667194195623,
    "lastPrice": 0.8191
  },
  "1INCHUSDT": {
    "createdAt": 1667194039767,
    "lastPrice": 0.6155
  },
  "GALAUSDT": {
    "createdAt": 1667194385339,
    "lastPrice": 0.04193
  },
  "OPUSDT": {
    "createdAt": 1667194086725,
    "lastPrice": 1.0518
  },
  "SFPUSDT": {
    "createdAt": 1667193924110,
    "lastPrice": 0.4048
  },
  "LPTUSDT": {
    "createdAt": 1667194208675,
    "lastPrice": 9.464
  },
  "ATAUSDT": {
    "createdAt": 1667194092160,
    "lastPrice": 0.1574
  },
  "PEOPLEUSDT": {
    "createdAt": 1667194335659,
    "lastPrice": 0.02006
  },
  "CELRUSDT": {
    "createdAt": 1667194108886,
    "lastPrice": 0.01528
  },
  "DYDXUSDT": {
    "createdAt": 1667194373351,
    "lastPrice": 1.697
  },
  "IOTXUSDT": {
    "createdAt": 1667193968653,
    "lastPrice": 0.02863
  },
  "SKLUSDT": {
    "createdAt": 1667193930769,
    "lastPrice": 0.03782
  },
  "SANDUSDT": {
    "createdAt": 1667194143565,
    "lastPrice": 0.889
  },
  "LITUSDT": {
    "createdAt": 1667194360661,
    "lastPrice": 0.848
  },
  "NKNUSDT": {
    "createdAt": 1667193908657,
    "lastPrice": 0.09102
  },
  "TOMOUSDT": {
    "createdAt": 1667194360835,
    "lastPrice": 0.4388
  },
  "RLCUSDT": {
    "createdAt": 1667194050279,
    "lastPrice": 1.0429
  },
  "GMTUSDT": {
    "createdAt": 1667194152115,
    "lastPrice": 0.5319
  },
  "WOOUSDT": {
    "createdAt": 1667193971766,
    "lastPrice": 0.18085
  },
  "ALICEUSDT": {
    "createdAt": 1667194235876,
    "lastPrice": 1.699
  },
  "COMPUSDT": {
    "createdAt": 1667194225956,
    "lastPrice": 50.72
  },
  "FLMUSDT": {
    "createdAt": 1667194202067,
    "lastPrice": 0.1147
  },
  "ALPHAUSDT": {
    "createdAt": 1667194291801,
    "lastPrice": 0.12
  },
  "OCEANUSDT": {
    "createdAt": 1667194459733,
    "lastPrice": 0.17846
  },
  "WAVESUSDT": {
    "createdAt": 1667194038850,
    "lastPrice": 3.485
  },
  "OMGUSDT": {
    "createdAt": 1667194038851,
    "lastPrice": 1.672
  },
  "HOTUSDT": {
    "createdAt": 1667194295635,
    "lastPrice": 0.002076
  },
  "BAKEUSDT": {
    "createdAt": 1667194433559,
    "lastPrice": 0.25
  },
  "RAYUSDT": {
    "createdAt": 1667194233621,
    "lastPrice": 0.526
  },
  "AUDIOUSDT": {
    "createdAt": 1667194361326,
    "lastPrice": 0.1973
  },
  "ROSEUSDT": {
    "createdAt": 1667194233547,
    "lastPrice": 0.06163
  },
  "API3USDT": {
    "createdAt": 1667194301033,
    "lastPrice": 1.736
  },
  "FOOTBALLUSDT": {
    "createdAt": 1667194414252,
    "lastPrice": 863.06
  },
  "BLZUSDT": {
    "createdAt": 1667194429853,
    "lastPrice": 0.08008
  },
  "UNFIUSDT": {
    "createdAt": 1667194054339,
    "lastPrice": 6.025
  },
  "CHZUSDT": {
    "createdAt": 1667193914072,
    "lastPrice": 0.22566
  },
  "HNTUSDT": {
    "createdAt": 1667194231249,
    "lastPrice": 4.027
  },
  "1000LUNCUSDT": {
    "createdAt": 1667194423307,
    "lastPrice": 0.2475
  },
  "LUNA2USDT": {
    "createdAt": 1667193941346,
    "lastPrice": 2.4539
  },
  "CVXUSDT": {
    "createdAt": 1667194234340,
    "lastPrice": 5.361
  },
  "LDOUSDT": {
    "createdAt": 1667193962216,
    "lastPrice": 1.531
  },
  "APTUSDT": {
    "createdAt": 1667193886693,
    "lastPrice": 8.175
  },
  "QNTUSDT": {
    "createdAt": 1667194404473,
    "lastPrice": 165.55
  }
}