{
  "https://167.86.71.48/no-limit-2022/": [
    {
      "type": "Download No Limit",
      "subType": "480p",
      "link": "https://acefile.co/f/84133234/nomit-2022-480p-nf-webrip-x264-drays-mkv",
      "server": "Googledrive"
    },
    {
      "type": "Download No Limit",
      "subType": "480p",
      "link": "https://1fichier.com/?pq0gi203rtpvfx9r4xpd",
      "server": "1fichier"
    },
    {
      "type": "Download No Limit",
      "subType": "480p",
      "link": "https://mega.nz/file/o5g23IgK#fKy3itwmAjkwDIPYypfllEx_4bspKC68bun2TdNemTk",
      "server": "Mega"
    },
    {
      "type": "Download No Limit",
      "subType": "480p",
      "link": "https://uptobox.com/oddaftzxbnos",
      "server": "Uptobox"
    },
    {
      "type": "Download No Limit",
      "subType": "720p",
      "link": "https://acefile.co/f/84133236/nomit-2022-720p-nf-webrip-x264-drays-mkv",
      "server": "Googledrive"
    },
    {
      "type": "Download No Limit",
      "subType": "720p",
      "link": "https://1fichier.com/?6ueg0pc87bap54w2bd6n",
      "server": "1fichier"
    },
    {
      "type": "Download No Limit",
      "subType": "720p",
      "link": "https://mega.nz/file/lphTCa5B#dMc9tV5rOwMVYiLCwvq_yY22tkjbuucUJlC5dsgWzro",
      "server": "Mega"
    },
    {
      "type": "Download No Limit",
      "subType": "720p",
      "link": "https://uptobox.com/icm77jf7hc26",
      "server": "Uptobox"
    },
    {
      "type": "Download No Limit",
      "subType": "1080p",
      "link": "https://acefile.co/f/84133238/nomit-2022-1080p-nf-webrip-x264-drays-mkv",
      "server": "Googledrive"
    },
    {
      "type": "Download No Limit",
      "subType": "1080p",
      "link": "https://1fichier.com/?2acihtlxpt5s2jnditzx",
      "server": "1fichier"
    },
    {
      "type": "Download No Limit",
      "subType": "1080p",
      "link": "https://mega.nz/file/l1IHkSZb#oMrBpQuMiSy-f7TCsHghmffCFYUhqHa-uVFxX0INtXE",
      "server": "Mega"
    },
    {
      "type": "Download No Limit",
      "subType": "1080p",
      "link": "https://uptobox.com/nf9kafwkgu3i",
      "server": "Uptobox"
    }
  ],
  "https://167.86.71.48/cyberpunk-edgerunners-2022/": [
    {
      "type": "|BATCH|",
      "subType": "Batch 720p",
      "server": "GDrive",
      "link": "https://acefile.co/f/83824834/cyberpunk-edgerunners-s1-720p-nf-webrip-x264-drays-rar"
    },
    {
      "type": "|BATCH|",
      "subType": "Batch 720p",
      "server": "Mega",
      "link": "https://mega.nz/file/l8pDTDCI#oRl3BRcdHvPjBPRhF4tXMgcAvhD3V7iZQsaQClCicTg"
    },
    {
      "type": "|BATCH|",
      "subType": "Batch 720p",
      "server": "1Fichier",
      "link": "https://1fichier.com/?nbb7fxdebs5bghi694w5"
    },
    {
      "type": "|BATCH|",
      "subType": "Batch 720p",
      "server": "Uptobox",
      "link": "https://uptobox.com/ezq8x1goe6ks"
    },
    {
      "type": "|BATCH|",
      "subType": "Batch 1080p",
      "server": "GDrive",
      "link": "https://acefile.co/f/83824837/cyberpunk-edgerunners-s1-1080p-nf-webrip-x264-drays-rar"
    },
    {
      "type": "|BATCH|",
      "subType": "Batch 1080p",
      "server": "Mega",
      "link": "https://mega.nz/file/lhBnxRbL#T4sgehSdKXCaZsPR1GDKZMKOaGbT4srDrYTb28WDsok"
    },
    {
      "type": "|BATCH|",
      "subType": "Batch 1080p",
      "server": "1Fichier",
      "link": "https://1fichier.com/?n7zlexu5kjtnxbfa5rkz"
    },
    {
      "type": "|BATCH|",
      "subType": "Batch 1080p",
      "server": "Uptobox",
      "link": "https://uptobox.com/7wt8bjjgr0ec"
    },
    {
      "type": "|Episode|Resolusi 720p|",
      "subType": "Episode 1",
      "server": "GD",
      "link": "https://acefile.co/f/83822565/cyberpunk-edgerunners-s1e01-let-you-down-720p-nf-webrip-x264-drays-mkv"
    },
    {
      "type": "|Episode|Resolusi 720p|",
      "subType": "Episode 1",
      "server": "Mega",
      "link": "https://mega.nz/file/5th2FIDC#pESDAKmqEZQECIE5t_0T-MLvs0OLEsRYP2hvROljGSk"
    },
    {
      "type": "|Episode|Resolusi 720p|",
      "subType": "Episode 2",
      "server": "GD",
      "link": "https://acefile.co/f/83822566/cyberpunk-edgerunners-s1e02ke-a-boy-720p-nf-webrip-x264-drays-mkv"
    },
    {
      "type": "|Episode|Resolusi 720p|",
      "subType": "Episode 2",
      "server": "Mega",
      "link": "https://mega.nz/file/otI2lZBB#wktrm-BH4aKZeKYGi4jpy-2BRr8Wm5mzXsvtlDAOVhg"
    },
    {
      "type": "|Episode|Resolusi 720p|",
      "subType": "Episode 3",
      "server": "GD",
      "link": "https://acefile.co/f/83822568/cyberpunk-edgerunners-s1e03-smooth-criminal-720p-nf-webrip-x264-drays-mkv"
    },
    {
      "type": "|Episode|Resolusi 720p|",
      "subType": "Episode 3",
      "server": "Mega",
      "link": "https://mega.nz/file/84JBkThK#v4MI4bLz08fQraK3ETgESRjtgjru-hKnu0Vu21WNuwk"
    },
    {
      "type": "|Episode|Resolusi 720p|",
      "subType": "Episode 4",
      "server": "GD",
      "link": "https://acefile.co/f/83822571/cyberpunk-edgerunners-s1e04-lucky-you-720p-nf-webrip-x264-drays-mkv"
    },
    {
      "type": "|Episode|Resolusi 720p|",
      "subType": "Episode 4",
      "server": "Mega",
      "link": "https://mega.nz/file/k0ZzgQIK#f5QZEPXW9g1aWPLnTz956VMjWGGEB-G0Yj8-6SiqDuw"
    },
    {
      "type": "|Episode|Resolusi 720p|",
      "subType": "Episode 5",
      "server": "GD",
      "link": "https://acefile.co/f/83822573/cyberpunk-edgerunners-s1e05-all-eyez-me-720p-nf-webrip-x264-drays-mkv"
    },
    {
      "type": "|Episode|Resolusi 720p|",
      "subType": "Episode 5",
      "server": "Mega",
      "link": "https://mega.nz/file/cwQAHJQD#z6_Muwqd31u173MfyjoemAP4l54HpflYLN0l3ZLRw74"
    },
    {
      "type": "|Episode|Resolusi 720p|",
      "subType": "Episode 6",
      "server": "GD",
      "link": "https://acefile.co/f/83822575/cyberpunk-edgerunners-s1e06-girl-fire-720p-nf-webrip-x264-drays-mkv"
    },
    {
      "type": "|Episode|Resolusi 720p|",
      "subType": "Episode 6",
      "server": "Mega",
      "link": "https://mega.nz/file/ptgzQRCJ#uv4Tu8AXnkrOtrybBmPX65GJLGrBta6hJ1ivg-s6KCU"
    },
    {
      "type": "|Episode|Resolusi 720p|",
      "subType": "Episode 7",
      "server": "GD",
      "link": "https://acefile.co/f/83822576/cyberpunk-edgerunners-s1e07-stronger-720p-nf-webrip-x264-drays-mkv"
    },
    {
      "type": "|Episode|Resolusi 720p|",
      "subType": "Episode 7",
      "server": "Mega",
      "link": "https://mega.nz/file/Ywg3yQQa#KE3-56mCD8ziVJb4uq86r5I4otI7Jcef_mUWachjPig"
    },
    {
      "type": "|Episode|Resolusi 720p|",
      "subType": "Episode 8",
      "server": "GD",
      "link": "https://acefile.co/f/83822577/cyberpunk-edgerunners-s1e08-stay-720p-nf-webrip-x264-drays-mkv"
    },
    {
      "type": "|Episode|Resolusi 720p|",
      "subType": "Episode 8",
      "server": "Mega",
      "link": "https://mega.nz/file/pwpThRiA#odm92jqKBmYBPxprpfenxKwzLgNe8GAGlp7XkZ-Oi2I"
    },
    {
      "type": "|Episode|Resolusi 720p|",
      "subType": "Episode 9",
      "server": "GD",
      "link": "https://acefile.co/f/83822580/cyberpunk-edgerunners-s1e09-humanity-720p-nf-webrip-x264-drays-mkv"
    },
    {
      "type": "|Episode|Resolusi 720p|",
      "subType": "Episode 9",
      "server": "Mega",
      "link": "https://mega.nz/file/xsIwRISa#iPimKVJD7XZyOFJOYEi-H0Bm2Pn4PEYvnOxZy_n3q2Y"
    },
    {
      "type": "|Episode|Resolusi 720p|",
      "subType": "Episode 10",
      "server": "GD",
      "link": "https://acefile.co/f/83822581/cyberpunk-edgerunners-s1e10-my-moon-my-man-720p-nf-webrip-x264-drays-mkv"
    },
    {
      "type": "|Episode|Resolusi 720p|",
      "subType": "Episode 10",
      "server": "Mega",
      "link": "https://mega.nz/file/c9ozSahY#4vKH9xJkf9P20SbWgcIXWwhJeP2pZTnL1mXd0lzVWNE"
    },
    {
      "type": "|Episode|Resolusi 1080p|",
      "subType": "Episode 1",
      "server": "GD",
      "link": "https://acefile.co/f/83824374/cyberpunk-edgerunners-s1e01-let-you-down-1080p-nf-webrip-x264-drays-mkv"
    },
    {
      "type": "|Episode|Resolusi 1080p|",
      "subType": "Episode 1",
      "server": "Mega",
      "link": "https://mega.nz/file/p4wDXRjZ#fVmpvXOVF6Kpvn0UEBi-4ypmCEKIIYKxVxbDmzindHk"
    },
    {
      "type": "|Episode|Resolusi 1080p|",
      "subType": "Episode 2",
      "server": "GD",
      "link": "https://acefile.co/f/83824376/cyberpunk-edgerunners-s1e02ke-a-boy-1080p-nf-webrip-x264-drays-mkv"
    },
    {
      "type": "|Episode|Resolusi 1080p|",
      "subType": "Episode 2",
      "server": "Mega",
      "link": "https://mega.nz/file/5hRE0TYZ#otjXXuw893eCWNxKxzH2iF8Der6yESi89gKXHzQ0-Sg"
    },
    {
      "type": "|Episode|Resolusi 1080p|",
      "subType": "Episode 3",
      "server": "GD",
      "link": "https://acefile.co/f/83824379/cyberpunk-edgerunners-s1e03-smooth-criminal-1080p-nf-webrip-x264-drays-mkv"
    },
    {
      "type": "|Episode|Resolusi 1080p|",
      "subType": "Episode 3",
      "server": "Mega",
      "link": "https://mega.nz/file/c8IjQIZQ#dncyRrhJpzhDSB0RoDfDrOL8EcMlp6gqQ6LkwRxWwso"
    },
    {
      "type": "|Episode|Resolusi 1080p|",
      "subType": "Episode 4",
      "server": "GD",
      "link": "https://acefile.co/f/83824382/cyberpunk-edgerunners-s1e04-lucky-you-1080p-nf-webrip-x264-drays-mkv"
    },
    {
      "type": "|Episode|Resolusi 1080p|",
      "subType": "Episode 4",
      "server": "Mega",
      "link": "https://mega.nz/file/Zhxm3bSK#wewtI4zx7VMurdped7X0AdDDKR5zbH7sqkfVFe1VlWY"
    },
    {
      "type": "|Episode|Resolusi 1080p|",
      "subType": "Episode 5",
      "server": "GD",
      "link": "https://acefile.co/f/83824388/cyberpunk-edgerunners-s1e05-all-eyez-me-1080p-nf-webrip-x264-drays-mkv"
    },
    {
      "type": "|Episode|Resolusi 1080p|",
      "subType": "Episode 5",
      "server": "Mega",
      "link": "https://mega.nz/file/twgiDSQI#XZnBUkyK_6S-btaKWAbEUmNrNc3bWOLiMQZ5iagxoyQ"
    },
    {
      "type": "|Episode|Resolusi 1080p|",
      "subType": "Episode 6",
      "server": "GD",
      "link": "https://acefile.co/f/83824390/cyberpunk-edgerunners-s1e06-girl-fire-1080p-nf-webrip-x264-drays-mkv"
    },
    {
      "type": "|Episode|Resolusi 1080p|",
      "subType": "Episode 6",
      "server": "Mega",
      "link": "https://mega.nz/file/EgBCyTLD#Zn81TPxOdl19vAkhyQCIrEujz9kVjlqsmS0bD7zMSw4"
    },
    {
      "type": "|Episode|Resolusi 1080p|",
      "subType": "Episode 7",
      "server": "GD",
      "link": "https://acefile.co/f/83824392/cyberpunk-edgerunners-s1e07-stronger-1080p-nf-webrip-x264-drays-mkv"
    },
    {
      "type": "|Episode|Resolusi 1080p|",
      "subType": "Episode 7",
      "server": "Mega",
      "link": "https://mega.nz/file/w1phSBCT#DWPSvULmUJ5zl7FMO7EXAUn1qtIAF3qCAuH7zyLmJbc"
    },
    {
      "type": "|Episode|Resolusi 1080p|",
      "subType": "Episode 8",
      "server": "GD",
      "link": "https://acefile.co/f/83824393/cyberpunk-edgerunners-s1e08-stay-1080p-nf-webrip-x264-drays-mkv"
    },
    {
      "type": "|Episode|Resolusi 1080p|",
      "subType": "Episode 8",
      "server": "Mega",
      "link": "https://mega.nz/file/Yk4j2B7R#wLhKNhIFcslYjlSCqPM6usWAdP4KMw7dL5uen-Baxrk"
    },
    {
      "type": "|Episode|Resolusi 1080p|",
      "subType": "Episode 9",
      "server": "GD",
      "link": "https://acefile.co/f/83824394/cyberpunk-edgerunners-s1e09-humanity-1080p-nf-webrip-x264-drays-mkv"
    },
    {
      "type": "|Episode|Resolusi 1080p|",
      "subType": "Episode 9",
      "server": "Mega",
      "link": "https://mega.nz/file/hx4GiARA#grhQ0O2VKw_tuadIbC9vXv44tKopEpZ2oai9tjFPWWk"
    },
    {
      "type": "|Episode|Resolusi 1080p|",
      "subType": "Episode 10",
      "server": "GD",
      "link": "https://acefile.co/f/83824395/cyberpunk-edgerunners-s1e10-my-moon-my-man-1080p-nf-webrip-x264-drays-mkv"
    },
    {
      "type": "|Episode|Resolusi 1080p|",
      "subType": "Episode 10",
      "server": "Mega",
      "link": "https://mega.nz/file/UswzSRhB#qShoPlX9gaC9EZBSEhFrtXreb1WMiNerrkl6MX0jS90"
    }
  ],
  "https://167.86.71.48/the-place-beyond-the-pines-2013/": [
    {
      "type": "Download The Place Beyond the Pines",
      "subType": "480p",
      "link": "https://acefile.co/f/84133254/the-place-beyond-the-pines-2013-480p-bluray-x264-drays-mkv",
      "server": "Googledrive"
    },
    {
      "type": "Download The Place Beyond the Pines",
      "subType": "480p",
      "link": "https://1fichier.com/?b86equaptg047aqieoq9",
      "server": "1fichier"
    },
    {
      "type": "Download The Place Beyond the Pines",
      "subType": "480p",
      "link": "https://mega.nz/file/B8gHFZYK#T1edpI5qbhATuNY-yxBtGuXQB4VGwK_-TM1J3Li8g98",
      "server": "Mega"
    },
    {
      "type": "Download The Place Beyond the Pines",
      "subType": "480p",
      "link": "https://uptobox.com/xtwhze53ohcu",
      "server": "Uptobox"
    },
    {
      "type": "Download The Place Beyond the Pines",
      "subType": "720p",
      "link": "https://acefile.co/f/84133259/the-place-beyond-the-pines-2013-720p-bluray-x264-drays-mkv",
      "server": "Googledrive"
    },
    {
      "type": "Download The Place Beyond the Pines",
      "subType": "720p",
      "link": "https://1fichier.com/?p928vujvno7j1oz7hjrl",
      "server": "1fichier"
    },
    {
      "type": "Download The Place Beyond the Pines",
      "subType": "720p",
      "link": "https://mega.nz/file/Y4B01Yjb#Ag8mY5XWWQmup4nWH6Ka3uEQqmMI0Uo08SuSJZEYbDY",
      "server": "Mega"
    },
    {
      "type": "Download The Place Beyond the Pines",
      "subType": "720p",
      "link": "https://uptobox.com/s7p6hv9w6vnc",
      "server": "Uptobox"
    },
    {
      "type": "Download The Place Beyond the Pines",
      "subType": "1080p",
      "link": "https://acefile.co/f/84133253/the-place-beyond-the-pines-2012-1080p-bluray-x264-drays-mkv",
      "server": "Googledrive"
    },
    {
      "type": "Download The Place Beyond the Pines",
      "subType": "1080p",
      "link": "https://1fichier.com/?6dmfgd1or67z1s7ygb1i",
      "server": "1fichier"
    },
    {
      "type": "Download The Place Beyond the Pines",
      "subType": "1080p",
      "link": "https://mega.nz/file/VtwzyA5J#ZjIM3sHFRRiQ9lpOIpOtjJD4QNsRTWfVzYHklgW5L-0",
      "server": "Mega"
    },
    {
      "type": "Download The Place Beyond the Pines",
      "subType": "1080p",
      "link": "https://uptobox.com/sdbceuugpg6g",
      "server": "Uptobox"
    }
  ],
  "https://167.86.71.48/rebecca-1940/": [
    {
      "type": "Download Rebecca",
      "subType": "480p",
      "link": "https://acefile.co/f/84133240/rebecca-1940-480p-bluray-x264-drays-mkv",
      "server": "Googledrive"
    },
    {
      "type": "Download Rebecca",
      "subType": "480p",
      "link": "https://1fichier.com/?sntaitpy32c3eu8enex0",
      "server": "1fichier"
    },
    {
      "type": "Download Rebecca",
      "subType": "480p",
      "link": "https://mega.nz/file/ZspAFb4K#d7-EKLBKb7g3k2Oo6aLzhw-t9rEqiuGLTxMjtfcHuDA",
      "server": "Mega"
    },
    {
      "type": "Download Rebecca",
      "subType": "480p",
      "link": "https://uptobox.com/z7iiicbdyvev",
      "server": "Uptobox"
    },
    {
      "type": "Download Rebecca",
      "subType": "720p",
      "link": "https://acefile.co/f/84133242/rebecca-1940-720p-bluray-x264-drays-mkv",
      "server": "Googledrive"
    },
    {
      "type": "Download Rebecca",
      "subType": "720p",
      "link": "https://1fichier.com/?1r8oatnmt7f7gv7brj54",
      "server": "1fichier"
    },
    {
      "type": "Download Rebecca",
      "subType": "720p",
      "link": "https://mega.nz/file/pth0DSBL#ypX5bx5wYli8ZIuYU3yNtrnYjmRwn_UMmxSCf1UClF0",
      "server": "Mega"
    },
    {
      "type": "Download Rebecca",
      "subType": "720p",
      "link": "https://uptobox.com/j57m3af5bdf3",
      "server": "Uptobox"
    },
    {
      "type": "Download Rebecca",
      "subType": "1080p",
      "link": "https://acefile.co/f/84133245/rebecca-1940-1080p-bluray-x264-drays-mkv",
      "server": "Googledrive"
    },
    {
      "type": "Download Rebecca",
      "subType": "1080p",
      "link": "https://1fichier.com/?kfptu5r0i4gz0gy3wv9x",
      "server": "1fichier"
    },
    {
      "type": "Download Rebecca",
      "subType": "1080p",
      "link": "https://mega.nz/file/MgwhyBwL#BpRV95V-r1OmAwUWPn8C3lnzWxsbz-XXXvnzVFx8swA",
      "server": "Mega"
    },
    {
      "type": "Download Rebecca",
      "subType": "1080p",
      "link": "https://uptobox.com/566iblt8wfx1",
      "server": "Uptobox"
    }
  ],
  "https://167.86.71.48/jujutsu-kaisen-0-2021/": [
    {
      "type": "Download Jujutsu Kaisen 0",
      "subType": "480p",
      "link": "https://acefile.co/f/84133226/jujutsu-kaisen-0-the-movie-2021-480p-bluray-x264-drays-mkv",
      "server": "Googledrive"
    },
    {
      "type": "Download Jujutsu Kaisen 0",
      "subType": "480p",
      "link": "https://1fichier.com/?bswv1x9jjhdu8fp5ehat",
      "server": "1fichier"
    },
    {
      "type": "Download Jujutsu Kaisen 0",
      "subType": "480p",
      "link": "https://mega.nz/file/M0o2RCRI#D7s-wET9wD5JeFsY-GjseF8Zi6lMsJQ7arXOS-ILsh4",
      "server": "Mega"
    },
    {
      "type": "Download Jujutsu Kaisen 0",
      "subType": "480p",
      "link": "https://uptobox.com/y0gdti8xmzho",
      "server": "Uptobox"
    },
    {
      "type": "Download Jujutsu Kaisen 0",
      "subType": "720p",
      "link": "https://acefile.co/f/84133229/jujutsu-kaisen-0-the-movie-2021-720p-bluray-x264-drays-mkv",
      "server": "Googledrive"
    },
    {
      "type": "Download Jujutsu Kaisen 0",
      "subType": "720p",
      "link": "https://1fichier.com/?lrpzyguyv8kdmg00d7dh",
      "server": "1fichier"
    },
    {
      "type": "Download Jujutsu Kaisen 0",
      "subType": "720p",
      "link": "https://mega.nz/file/BgZDzSrB#LqhbMgLQ_3yle0ulSO77pFNZv0rr-6hUkC87GhMi-j8",
      "server": "Mega"
    },
    {
      "type": "Download Jujutsu Kaisen 0",
      "subType": "720p",
      "link": "https://uptobox.com/pgcalfukma82",
      "server": "Uptobox"
    },
    {
      "type": "Download Jujutsu Kaisen 0",
      "subType": "1080p",
      "link": "https://acefile.co/f/84133231/jujutsu-kaisen-0-the-movie-2021-1080p-bluray-x264-drays-mkv",
      "server": "Googledrive"
    },
    {
      "type": "Download Jujutsu Kaisen 0",
      "subType": "1080p",
      "link": "https://1fichier.com/?5yzne1lhb5e49lf4hbg6",
      "server": "1fichier"
    },
    {
      "type": "Download Jujutsu Kaisen 0",
      "subType": "1080p",
      "link": "https://mega.nz/file/E152EKRK#dBcF4xp63Hyfgg7uZ8_iRPZyAI-OY3osLQp8CUzT7MQ",
      "server": "Mega"
    },
    {
      "type": "Download Jujutsu Kaisen 0",
      "subType": "1080p",
      "link": "https://uptobox.com/wg44q3uw1s4m",
      "server": "Uptobox"
    }
  ]
}